pyitc-1.1.0.dist-info/METADATA
pyitc-1.1.0.dist-info/RECORD
pyitc-1.1.0.dist-info/WHEEL
pyitc-1.1.0.dist-info/LICENSE
pyitc/exceptions.py
pyitc/pyitc.py
pyitc/_pyitc.abi3.so
pyitc/__init__.py
pyitc/extended_api.py
pyitc/util.py
pyitc/_internals/wrappers.py
pyitc/_internals/__init__.py
