Metadata-Version: 2.1
Name: pyitc
Version: 1.1.0
Summary: Python bindings for the libitc library
Keywords: interval,tree,clocks,logical,vector,causal,sync
License:                     GNU AFFERO GENERAL PUBLIC LICENSE
Classifier: Development Status :: 5 - Production/Stable
Classifier: Intended Audience :: Developers
Classifier: Intended Audience :: Education
Classifier: Intended Audience :: Science/Research
Classifier: Programming Language :: Python :: 3
Classifier: Programming Language :: Python :: 3.8
Classifier: Programming Language :: Python :: 3.9
Classifier: Programming Language :: Python :: 3.10
Classifier: Programming Language :: Python :: 3.11
Classifier: Programming Language :: Python :: 3.12
Classifier: Programming Language :: Python :: 3.13
Project-URL: repository, https://github.com/astro-stan/pyitc
Project-URL: homepage, https://github.com/astro-stan/pyitc
Project-URL: issues, https://github.com/astro-stan/pyitc/issues
Project-URL: changelog, https://github.com/astro-stan/pyitc/releases
Requires-Python: >=3.8
Requires-Dist: cffi>=1.16
Requires-Dist: typing-extensions; python_version < "3.11"
